{"kind":"identitytoolkit#DownloadAccountResponse","users":[{"localId":"kFBjf8k6niMgJRI5WaSIVn2ZuZeN","lastLoginAt":"1687123584333","emailVerified":false,"email":"jay@mail.com","salt":"fakeSaltoqMmvgDeI6ObYYIiuJ0G","passwordHash":"fakeHash:salt=fakeSaltoqMmvgDeI6ObYYIiuJ0G:password=123456","passwordUpdatedAt":1687123584333,"validSince":"1687123584","createdAt":"1687123584333","providerUserInfo":[{"providerId":"password","email":"jay@mail.com","federatedId":"jay@mail.com","rawId":"jay@mail.com"}],"lastRefreshAt":"2023-06-19T06:59:18.673Z"}]}